espFOTA.py
micropython_espFOTA-1.0.0.dist-info/LICENSE
micropython_espFOTA-1.0.0.dist-info/METADATA
micropython_espFOTA-1.0.0.dist-info/WHEEL
micropython_espFOTA-1.0.0.dist-info/top_level.txt
micropython_espFOTA-1.0.0.dist-info/RECORD
