Metadata-Version: 2.1
Name: micropython-espFOTA
Version: 1.0.0
Summary: "espFOTA: An OTA (Over-the-Air) update library for ESP8266, ESP32, and other devices supporting MicroPython.
Home-page: UNKNOWN
Author: Raghul Raj G
Author-email: raghulrajatmega328@gmail.com
License: UNKNOWN
Project-URL: Source, https://github.com/raghulrajg/espFOTA
Keywords: OTA,FOTA,Update,Microcontroller,Micropython
Platform: UNKNOWN
Classifier: Programming Language :: Python :: 3
Classifier: License :: OSI Approved :: GNU General Public License v3 (GPLv3)
Classifier: Intended Audience :: Developers
Classifier: Topic :: Software Development :: Libraries :: Python Modules
